_manylinux.py
manylinux_max-1.0.1.dist-info/LICENSE
manylinux_max-1.0.1.dist-info/METADATA
manylinux_max-1.0.1.dist-info/WHEEL
manylinux_max-1.0.1.dist-info/top_level.txt
manylinux_max-1.0.1.dist-info/RECORD
