Metadata-Version: 2.1
Name: manylinux_max
Version: 1.0.1
Summary: dynamically cap the version of manylinux when installing from pip
Home-page: https://github.com/asottile/manylinux-max
Author: Anthony Sottile
Author-email: asottile@umich.edu
License: MIT
Classifier: License :: OSI Approved :: MIT License
Classifier: Programming Language :: Python :: 3
Classifier: Programming Language :: Python :: 3 :: Only
Classifier: Programming Language :: Python :: Implementation :: CPython
Classifier: Programming Language :: Python :: Implementation :: PyPy
Requires-Python: >=3.7
License-File: LICENSE
